slave.v
module spi_slave (
  input sck,  
  input cs,
  input mosi,

  output reg [7:0] cmd,
  output reg [23:0] address,
  output reg [31:0] data
);

reg enable = 0;
reg mosi_out = 0;
reg unsigned [7:0] i = 0;
reg unsigned [7:0] counter = 0;
 
always @(posedge sck)
begin
   if (~cs)
   begin
      if (i <= 7)
      begin
        cmd[7-i] <= mosi;
      end
      else if (i >= 8 && i <= 31)
      begin
        address[31-i] <= mosi;
      end
      else
      begin
        data[63-i] <= mosi;
      end
      i = i + 1;
      counter = counter + 1;
      if (counter == 64)
        begin
          if (cmd == 8'hB5)
            enable=1;
        end
   end
end

always @(posedge enable)
begin
  if (cmd == 8'hB5)
    begin
      for (i=0;i<=23;i=i+1)
      begin
        mosi_out=address[23-i];
        #10;
      end
      for (i=0;i<=31;i=i+1)
      begin
        mosi_out=data[31-i];
        #10;
      end
      mosi_out=0;
    end
end

always @(posedge cs)
  begin
    counter=0;
    i=0;
  end

endmodule

testbench.v
module tb;
    reg sck = 0;
    reg cs=1;
    wire [63:0] data;
    reg mosi;
    reg unsigned [7:0] i;

    assign data[63:56] = 8'hB5; //команда
    assign data[55:32] = 24'h123456; //адрес
    assign data[31:0] = 32'h789456; //данные

    // initial
    //    forever #10 sck=~sck;

    initial
    begin
        mosi=0;
        #50;
        cs=0;
        for (i=0;i<=63;i=i+1)
            begin 
                mosi=data[63-i];
                #5;
                sck=1;
                #10;
                sck=0;
                #5;
            end
        cs=1;
    end

    initial
    begin
        #5000 $finish;
    end

    initial
    begin
        $dumpfile("spi_dump.vcd");
        $dumpvars(0, tb);
    end

    spi_slave spi0(
        .sck(sck),
        .cs(cs),
        .mosi(mosi)
    );

endmodule

spi_dump.vcd
$date
	Tue Nov 29 16:08:41 2022
$end
$version
	Icarus Verilog
$end
$timescale
	1s
$end
$scope module tb $end
$var wire 64 ! data [63:0] $end
$var reg 1 " cs $end
$var reg 8 # i [7:0] $end
$var reg 1 $ mosi $end
$var reg 1 % sck $end
$scope module spi0 $end
$var wire 1 " cs $end
$var wire 1 $ mosi $end
$var wire 1 % sck $end
$var reg 24 & address [23:0] $end
$var reg 8 ' cmd [7:0] $end
$var reg 8 ( counter [7:0] $end
$var reg 32 ) data [31:0] $end
$var reg 1 * enable $end
$var reg 8 + i [7:0] $end
$var reg 1 , mosi_out $end
$upscope $end
$upscope $end
$enddefinitions $end
$comment Show the parameter values. $end
$dumpall
$end
#0
$dumpvars
0,
b0 +
0*
bx )
b0 (
bx '
bx &
0%
0$
bx #
1"
b10100010010001101000101011000000000011110001001010001010110 !
$end
#50
b0 #
0"
#55
b0xxxxxxx '
b1 (
b1 +
1%
#65
0%
#70
b1 #
#75
b0xxxxxx '
b10 (
b10 +
1%
#85
0%
#90
b10 #
#95
b0xxxxx '
b11 (
b11 +
1%
#105
0%
#110
b11 #
#115
b0xxxx '
b100 (
b100 +
1%
#125
0%
#130
b100 #
#135
b0xxx '
b101 (
b101 +
1%
#145
0%
#150
1$
b101 #
#155
b1xx '
b110 (
b110 +
1%
#165
0%
#170
0$
b110 #
#175
b10x '
b111 (
b111 +
1%
#185
0%
#190
1$
b111 #
#195
b101 '
b1000 (
b1000 +
1%
#205
0%
#210
0$
b1000 #
#215
b0xxxxxxxxxxxxxxxxxxxxxxx &
b1001 (
b1001 +
1%
#225
0%
#230
b1001 #
#235
b0xxxxxxxxxxxxxxxxxxxxxx &
b1010 (
b1010 +
1%
#245
0%
#250
b1010 #
#255
b0xxxxxxxxxxxxxxxxxxxxx &
b1011 (
b1011 +
1%
#265
0%
#270
1$
b1011 #
#275
b1xxxxxxxxxxxxxxxxxxxx &
b1100 (
b1100 +
1%
#285
0%
#290
0$
b1100 #
#295
b10xxxxxxxxxxxxxxxxxxx &
b1101 (
b1101 +
1%
#305
0%
#310
b1101 #
#315
b100xxxxxxxxxxxxxxxxxx &
b1110 (
b1110 +
1%
#325
0%
#330
1$
b1110 #
#335
b1001xxxxxxxxxxxxxxxxx &
b1111 (
b1111 +
1%
#345
0%
#350
0$
b1111 #
#355
b10010xxxxxxxxxxxxxxxx &
b10000 (
b10000 +
1%
#365
0%
#370
b10000 #
#375
b100100xxxxxxxxxxxxxxx &
b10001 (
b10001 +
1%
#385
0%
#390
b10001 #
#395
b1001000xxxxxxxxxxxxxx &
b10010 (
b10010 +
1%
#405
0%
#410
1$
b10010 #
#415
b10010001xxxxxxxxxxxxx &
b10011 (
b10011 +
1%
#425
0%
#430
b10011 #
#435
b100100011xxxxxxxxxxxx &
b10100 (
b10100 +
1%
#445
0%
#450
0$
b10100 #
#455
b1001000110xxxxxxxxxxx &
b10101 (
b10101 +
1%
#465
0%
#470
1$
b10101 #
#475
b10010001101xxxxxxxxxx &
b10110 (
b10110 +
1%
#485
0%
#490
0$
b10110 #
#495
b100100011010xxxxxxxxx &
b10111 (
b10111 +
1%
#505
0%
#510
b10111 #
#515
b1001000110100xxxxxxxx &
b11000 (
b11000 +
1%
#525
0%
#530
b11000 #
#535
b10010001101000xxxxxxx &
b11001 (
b11001 +
1%
#545
0%
#550
1$
b11001 #
#555
b100100011010001xxxxxx &
b11010 (
b11010 +
1%
#565
0%
#570
0$
b11010 #
#575
b1001000110100010xxxxx &
b11011 (
b11011 +
1%
#585
0%
#590
1$
b11011 #
#595
b10010001101000101xxxx &
b11100 (
b11100 +
1%
#605
0%
#610
0$
b11100 #
#615
b100100011010001010xxx &
b11101 (
b11101 +
1%
#625
0%
#630
1$
b11101 #
#635
b1001000110100010101xx &
b11110 (
b11110 +
1%
#645
0%
#650
b11110 #
#655
b10010001101000101011x &
b11111 (
b11111 +
1%
#665
0%
#670
0$
b11111 #
#675
b100100011010001010110 &
b100000 (
b100000 +
1%
#685
0%
#690
b100000 #
#695
b0xxxxxxxxxxxxxxxxxxxxxxxxxxxxxxx )
b100001 (
b100001 +
1%
#705
0%
#710
b100001 #
#715
b0xxxxxxxxxxxxxxxxxxxxxxxxxxxxxx )
b100010 (
b100010 +
1%
#725
0%
#730
b100010 #
#735
b0xxxxxxxxxxxxxxxxxxxxxxxxxxxxx )
b100011 (
b100011 +
1%
#745
0%
#750
b100011 #
#755
b0xxxxxxxxxxxxxxxxxxxxxxxxxxxx )
b100100 (
b100100 +
1%
#765
0%
#770
b100100 #
#775
b0xxxxxxxxxxxxxxxxxxxxxxxxxxx )
b100101 (
b100101 +
1%
#785
0%
#790
b100101 #
#795
b0xxxxxxxxxxxxxxxxxxxxxxxxxx )
b100110 (
b100110 +
1%
#805
0%
#810
b100110 #
#815
b0xxxxxxxxxxxxxxxxxxxxxxxxx )
b100111 (
b100111 +
1%
#825
0%
#830
b100111 #
#835
b0xxxxxxxxxxxxxxxxxxxxxxxx )
b101000 (
b101000 +
1%
#845
0%
#850
b101000 #
#855
b0xxxxxxxxxxxxxxxxxxxxxxx )
b101001 (
b101001 +
1%
#865
0%
#870
1$
b101001 #
#875
b1xxxxxxxxxxxxxxxxxxxxxx )
b101010 (
b101010 +
1%
#885
0%
#890
b101010 #
#895
b11xxxxxxxxxxxxxxxxxxxxx )
b101011 (
b101011 +
1%
#905
0%
#910
b101011 #
#915
b111xxxxxxxxxxxxxxxxxxxx )
b101100 (
b101100 +
1%
#925
0%
#930
b101100 #
#935
b1111xxxxxxxxxxxxxxxxxxx )
b101101 (
b101101 +
1%
#945
0%
#950
0$
b101101 #
#955
b11110xxxxxxxxxxxxxxxxxx )
b101110 (
b101110 +
1%
#965
0%
#970
b101110 #
#975
b111100xxxxxxxxxxxxxxxxx )
b101111 (
b101111 +
1%
#985
0%
#990
b101111 #
#995
b1111000xxxxxxxxxxxxxxxx )
b110000 (
b110000 +
1%
#1005
0%
#1010
1$
b110000 #
#1015
b11110001xxxxxxxxxxxxxxx )
b110001 (
b110001 +
1%
#1025
0%
#1030
0$
b110001 #
#1035
b111100010xxxxxxxxxxxxxx )
b110010 (
b110010 +
1%
#1045
0%
#1050
b110010 #
#1055
b1111000100xxxxxxxxxxxxx )
b110011 (
b110011 +
1%
#1065
0%
#1070
1$
b110011 #
#1075
b11110001001xxxxxxxxxxxx )
b110100 (
b110100 +
1%
#1085
0%
#1090
0$
b110100 #
#1095
b111100010010xxxxxxxxxxx )
b110101 (
b110101 +
1%
#1105
0%
#1110
1$
b110101 #
#1115
b1111000100101xxxxxxxxxx )
b110110 (
b110110 +
1%
#1125
0%
#1130
0$
b110110 #
#1135
b11110001001010xxxxxxxxx )
b110111 (
b110111 +
1%
#1145
0%
#1150
b110111 #
#1155
b111100010010100xxxxxxxx )
b111000 (
b111000 +
1%
#1165
0%
#1170
b111000 #
#1175
b1111000100101000xxxxxxx )
b111001 (
b111001 +
1%
#1185
0%
#1190
1$
b111001 #
#1195
b11110001001010001xxxxxx )
b111010 (
b111010 +
1%
#1205
0%
#1210
0$
b111010 #
#1215
b111100010010100010xxxxx )
b111011 (
b111011 +
1%
#1225
0%
#1230
1$
b111011 #
#1235
b1111000100101000101xxxx )
b111100 (
b111100 +
1%
#1245
0%
#1250
0$
b111100 #
#1255
b11110001001010001010xxx )
b111101 (
b111101 +
1%
#1265
0%
#1270
1$
b111101 #
#1275
b111100010010100010101xx )
b111110 (
b111110 +
1%
#1285
0%
#1290
b111110 #
#1295
b1111000100101000101011x )
b111111 (
b111111 +
1%
#1305
0%
#1310
0$
b111111 #
#1315
b11110001001010001010110 )
b1000000 (
b1000000 +
1%
#1325
0%
#1330
b0 +
b0 (
1"
b1000000 #
